pyvchart/__init__.py
pyvchart/_version.py
pyvchart/globals.py
pyvchart/types.py
pyvchart/charts/__init__.py
pyvchart/charts/base.py
pyvchart/charts/chart.py
pyvchart/charts/mixins.py
pyvchart/charts/basic_charts/__init__.py
pyvchart/charts/basic_charts/area.py
pyvchart/charts/basic_charts/bar.py
pyvchart/charts/basic_charts/boxplot.py
pyvchart/charts/basic_charts/circle_packing.py
pyvchart/charts/basic_charts/circular_progress.py
pyvchart/charts/basic_charts/common.py
pyvchart/charts/basic_charts/correlation.py
pyvchart/charts/basic_charts/dot.py
pyvchart/charts/basic_charts/funnel.py
pyvchart/charts/basic_charts/gauge.py
pyvchart/charts/basic_charts/heatmap.py
pyvchart/charts/basic_charts/histogram.py
pyvchart/charts/basic_charts/line.py
pyvchart/charts/basic_charts/linear_progress.py
pyvchart/charts/basic_charts/link.py
pyvchart/charts/basic_charts/liquid.py
pyvchart/charts/basic_charts/map.py
pyvchart/charts/basic_charts/mosaic.py
pyvchart/charts/basic_charts/pictogram.py
pyvchart/charts/basic_charts/pie.py
pyvchart/charts/basic_charts/radar.py
pyvchart/charts/basic_charts/range_area.py
pyvchart/charts/basic_charts/range_column.py
pyvchart/charts/basic_charts/rose.py
pyvchart/charts/basic_charts/sankey.py
pyvchart/charts/basic_charts/scatter.py
pyvchart/charts/basic_charts/sequence.py
pyvchart/charts/basic_charts/sunburst.py
pyvchart/charts/basic_charts/treemap.py
pyvchart/charts/basic_charts/venn.py
pyvchart/charts/basic_charts/waterfall.py
pyvchart/charts/basic_charts/wordcloud.py
pyvchart/charts/three_axis_charts/__init__.py
pyvchart/charts/three_axis_charts/bar3D.py
pyvchart/charts/three_axis_charts/funnel3D.py
pyvchart/charts/three_axis_charts/wordCloud3D.py
pyvchart/commons/__init__.py
pyvchart/commons/utils.py
pyvchart/datasets/__init__.py
pyvchart/datasets/filename.json
pyvchart/options/__init__.py
pyvchart/options/charts_options.py
pyvchart/options/global_options.py
pyvchart/options/series_options.py
pyvchart/render/__init__.py
py_vchart-2.0.0.dist-info/LICENSE
py_vchart-2.0.0.dist-info/METADATA
py_vchart-2.0.0.dist-info/WHEEL
py_vchart-2.0.0.dist-info/top_level.txt
py_vchart-2.0.0.dist-info/RECORD
